pyding/__init__.py
pyding/event_space.py
pyding/exceptions.py
pyding/structures.py
pyding-1.8.3.dist-info/LICENSE
pyding-1.8.3.dist-info/METADATA
pyding-1.8.3.dist-info/WHEEL
pyding-1.8.3.dist-info/top_level.txt
pyding-1.8.3.dist-info/RECORD
