Metadata-Version: 2.1
Name: pyding
Version: 1.8.3
Summary: Simpĺe but effective event framework
Home-page: https://github.com/jaobernardi/pyding
Author: João Lucas Bernardi
Author-email: joao_bernardi@outlook.com
Classifier: Development Status :: 5 - Production/Stable
Classifier: Intended Audience :: Developers
Classifier: Topic :: Software Development :: Build Tools
Classifier: License :: OSI Approved :: GNU General Public License v3 (GPLv3)
Classifier: Programming Language :: Python :: 3.6
Classifier: Programming Language :: Python :: 3.7
Classifier: Programming Language :: Python :: 3.8
Classifier: Programming Language :: Python :: 3.9
Classifier: Programming Language :: Python :: 3.10
Requires-Python: >=3.6
License-File: LICENSE
